llm_scratch/__init__.py
llm_scratch/console.py
llm_scratch/image.py
llm_scratch/llm_scratch.py
llm_scratch/raga.py
llm_scratch/voice.py
llm_scratch-0.1.5.dist-info/METADATA
llm_scratch-0.1.5.dist-info/WHEEL
llm_scratch-0.1.5.dist-info/top_level.txt
llm_scratch-0.1.5.dist-info/RECORD
